LICENSE
steam/__init__.py
steam/__main__.py
steam/__metadata__.py
steam/_const.py
steam/_gc/__init__.py
steam/_gc/client.py
steam/_gc/state.py
steam/abc.py
steam/achievement.py
steam/app.py
steam/badge.py
steam/bundle.py
steam/channel.py
steam/chat.py
steam/clan.py
steam/client.py
steam/comment.py
steam/enums.py
steam/errors.py
steam/event.py
steam/ext/commands/__init__.py
steam/ext/commands/bot.py
steam/ext/commands/cog.py
steam/ext/commands/commands.py
steam/ext/commands/context.py
steam/ext/commands/converters.py
steam/ext/commands/cooldown.py
steam/ext/commands/errors.py
steam/ext/commands/help.py
steam/ext/commands/utils.py
steam/ext/csgo/__init__.py
steam/ext/csgo/backpack.py
steam/ext/csgo/client.py
steam/ext/csgo/enums.py
steam/ext/csgo/models.py
steam/ext/csgo/protobufs/__init__.py
steam/ext/csgo/protobufs/base.py
steam/ext/csgo/protobufs/cstrike.py
steam/ext/csgo/protobufs/econ.py
steam/ext/csgo/protobufs/engine.py
steam/ext/csgo/protobufs/sdk.py
steam/ext/csgo/protobufs/struct_messages.py
steam/ext/csgo/protobufs/system_messages.py
steam/ext/csgo/state.py
steam/ext/csgo/utils.py
steam/ext/tf2/__init__.py
steam/ext/tf2/backpack.py
steam/ext/tf2/client.py
steam/ext/tf2/currency.py
steam/ext/tf2/enums.py
steam/ext/tf2/protobufs/__init__.py
steam/ext/tf2/protobufs/base.py
steam/ext/tf2/protobufs/econ.py
steam/ext/tf2/protobufs/sdk.py
steam/ext/tf2/protobufs/struct_messages.py
steam/ext/tf2/protobufs/system_messages.py
steam/ext/tf2/protobufs/tf.py
steam/ext/tf2/py.typed
steam/ext/tf2/state.py
steam/ext/tf2/types/schema.py
steam/friend.py
steam/game_server.py
steam/gateway.py
steam/group.py
steam/guard.py
steam/http.py
steam/id.py
steam/invite.py
steam/leaderboard.py
steam/manifest.py
steam/media.py
steam/message.py
steam/models.py
steam/package.py
steam/post.py
steam/profile.py
steam/protobufs/__init__.py
steam/protobufs/app_info.py
steam/protobufs/auth.py
steam/protobufs/base.py
steam/protobufs/chat.py
steam/protobufs/clan.py
steamio-1.1.3.dist-info/LICENSE
steamio-1.1.3.dist-info/METADATA
steamio-1.1.3.dist-info/WHEEL
steamio-1.1.3.dist-info/RECORD
