Metadata-Version: 2.1
Name: steamio
Version: 1.1.3
Summary: A Python wrapper for the Steam API
License: MIT
Keywords: steam.py,steam,steamio,steam-api
Author: Gobot1234
Author-email: gobot1234yt@gmail.com
Requires-Python: >=3.11,<4.0
Classifier: Development Status :: 5 - Production/Stable
Classifier: Framework :: AsyncIO
Classifier: Intended Audience :: Developers
Classifier: License :: OSI Approved :: MIT License
Classifier: Natural Language :: English
Classifier: Operating System :: OS Independent
Classifier: Programming Language :: Python :: 3
Classifier: Programming Language :: Python :: 3.11
Classifier: Programming Language :: Python :: 3.12
Classifier: Programming Language :: Python :: 3.13
Classifier: Topic :: Software Development :: Libraries
Classifier: Topic :: Software Development :: Libraries :: Python Modules
Classifier: Typing :: Typed
Requires-Dist: aiohttp (>=3.8,<4.0)
Requires-Dist: beautifulsoup4 (>=4.10,<5.0)
Requires-Dist: betterproto (==2.0.0b6)
Requires-Dist: cryptography (>=41,<43)
Requires-Dist: typing-extensions (>=4.10.0,<5.0.0)
Requires-Dist: vdf (>=3.4,<4.0)
Requires-Dist: zstd (>=1.5.7.2,<2.0.0.0) ; python_version < "3.14"
Project-URL: Bug Tracker, https://github.com/Gobot1234/steam.py/issues
Project-URL: Code, https://github.com/Gobot1234/steam.py
Project-URL: Documentation, https://steam-py.github.io/docs/latest
